torba/__init__.py
torba/baseaccount.py
torba/basedatabase.py
torba/baseheader.py
torba/baseledger.py
torba/basenetwork.py
torba/basescript.py
torba/basetransaction.py
torba/bcd_data_stream.py
torba/bip32.py
torba/coinselection.py
torba/constants.py
torba/hash.py
torba/manager.py
torba/mnemonic.py
torba/stream.py
torba/util.py
torba/wallet.py
torba/coin/__init__.py
torba/coin/bitcoincash.py
torba/coin/bitcoinsegwit.py
torba/words/chinese_simplified.txt
torba/words/english.txt
torba/words/japanese.txt
torba/words/portuguese.txt
torba/words/spanish.txt
torba-0.0.3.dist-info/METADATA
torba-0.0.3.dist-info/RECORD
torba-0.0.3.dist-info/WHEEL
torba-0.0.3.dist-info/top_level.txt
