Metadata-Version: 2.1
Name: torba
Version: 0.0.3
Summary: Wallet library for bitcoin based currencies.
Home-page: https://github.com/lbryio/torba
Author: LBRY Inc.
Author-email: hello@lbry.io
License: MIT
Keywords: wallet,crypto,currency,money,bitcoin,lbry
Platform: UNKNOWN
Classifier: Framework :: Twisted
Classifier: Intended Audience :: Developers
Classifier: Intended Audience :: System Administrators
Classifier: License :: OSI Approved :: MIT License
Classifier: Programming Language :: Python :: 3
Classifier: Operating System :: OS Independent
Classifier: Topic :: Internet
Classifier: Topic :: Software Development :: Libraries :: Python Modules
Classifier: Topic :: System :: Distributed Computing
Classifier: Topic :: Utilities
Requires-Python: >=2.7
Provides-Extra: test
Requires-Dist: twisted
Requires-Dist: ecdsa
Requires-Dist: pbkdf2
Requires-Dist: cryptography
Requires-Dist: typing
Provides-Extra: test
Requires-Dist: mock; extra == 'test'
